t5s/__init__.py
t5s/__main__.py
t5s/cli.py
t5s-2.0.8.dist-info/LICENSE
t5s-2.0.8.dist-info/METADATA
t5s-2.0.8.dist-info/WHEEL
t5s-2.0.8.dist-info/entry_points.txt
t5s-2.0.8.dist-info/top_level.txt
t5s-2.0.8.dist-info/RECORD
