Metadata-Version: 2.1
Name: t5s
Version: 2.0.8
Summary: T5 Summarisation Using Pytorch Lightning
Home-page: https://dagshub.com/gagan3012/summarization.git
License: MIT License
Platform: UNKNOWN
Classifier: Development Status :: 4 - Beta
Classifier: License :: OSI Approved :: MIT License
Classifier: Programming Language :: Python :: 3
Classifier: Operating System :: OS Independent
Requires-Python: >=3.6
Requires-Dist: numpy (==1.19.2)
Requires-Dist: datasets (==1.10.2)
Requires-Dist: pytorch-lightning (==1.3.5)
Requires-Dist: transformers (==4.9.0)
Requires-Dist: torch (==1.9.0)
Requires-Dist: dagshub (==0.1.7)
Requires-Dist: pandas (==1.1.5)
Requires-Dist: rouge-score (==0.0.4)
Requires-Dist: dvc (==2.5.4)
Requires-Dist: mlflow (==1.19.0)
Requires-Dist: streamlit (==0.85.1)
Requires-Dist: pyyaml
